airflow_providers/__init__.py
airflow_providers/backend/__init__.py
airflow_providers/backend/s3.py
airflow_providers/fs/__init__.py
airflow_providers/fs/s3.py
airflow_providers-0.3.0.dist-info/METADATA
airflow_providers-0.3.0.dist-info/WHEEL
airflow_providers-0.3.0.dist-info/RECORD
