Metadata-Version: 2.1
Name: airflow-providers
Version: 0.3.0
Summary: Custom providers for Apache Airflow
License: MIT
Author: Anonymous
Requires-Python: >=3.9
Classifier: License :: OSI Approved :: MIT License
Classifier: Programming Language :: Python :: 3
Classifier: Programming Language :: Python :: 3.9
Classifier: Programming Language :: Python :: 3.10
Classifier: Programming Language :: Python :: 3.11
Classifier: Programming Language :: Python :: 3.12
Requires-Dist: apache-airflow (>=2.0.0,<3.0.0)
Requires-Dist: apache-airflow-providers-amazon (>=5.0.0,<6.0.0)
Requires-Dist: botocore (>=1.0.0)
